envreport.py
envreport-0.0.1.dev0.dist-info/LICENSE
envreport-0.0.1.dev0.dist-info/METADATA
envreport-0.0.1.dev0.dist-info/WHEEL
envreport-0.0.1.dev0.dist-info/entry_points.txt
envreport-0.0.1.dev0.dist-info/top_level.txt
envreport-0.0.1.dev0.dist-info/RECORD
