Metadata-Version: 2.1
Name: envreport
Version: 0.0.1.dev0
Summary: envreport: compare environments
Author-email: Min RK <benjaminrk@gmail.com>
License: MIT
Project-URL: Source, https://github.com/minrk/envreport
Project-URL: Tracker, https://github.com/minrk/envreport/issues
Keywords: Environment
Classifier: Development Status :: 1 - Planning
Classifier: Intended Audience :: Developers
Classifier: Intended Audience :: System Administrators
Classifier: Intended Audience :: Science/Research
Classifier: License :: OSI Approved :: MIT License
Classifier: Programming Language :: Python
Classifier: Programming Language :: Python :: 3
Classifier: Operating System :: POSIX
Requires-Python: >=3.6
License-File: LICENSE
Provides-Extra: test
Requires-Dist: pytest ; extra == 'test'
